MANIFEST.in
README.md
requirements.txt
setup.py
ultraopt/__init__.py
ultraopt/__version__.py
ultraopt/constants.py
ultraopt/result.py
ultraopt/structure.py
ultraopt/viz.py
ultraopt.egg-info/PKG-INFO
ultraopt.egg-info/SOURCES.txt
ultraopt.egg-info/dependency_links.txt
ultraopt.egg-info/requires.txt
ultraopt.egg-info/top_level.txt
ultraopt/async_comm/__init__.py
ultraopt/async_comm/dispatcher.py
ultraopt/async_comm/master.py
ultraopt/async_comm/nameserver.py
ultraopt/async_comm/worker.py
ultraopt/benchmarks/__init__.py
ultraopt/benchmarks/synthetic_functions.py
ultraopt/facade/__init__.py
ultraopt/facade/fmin.py
ultraopt/facade/result.py
ultraopt/facade/utils.py
ultraopt/hdl/__init__.py
ultraopt/hdl/_hdl2cs.py
ultraopt/hdl/hp_def.py
ultraopt/hdl/utils.py
ultraopt/hdl/viz.py
ultraopt/learning/__init__.py
ultraopt/learning/tpe.py
ultraopt/multi_fidelity/__init__.py
ultraopt/multi_fidelity/iter/__init__.py
ultraopt/multi_fidelity/iter/base_iter.py
ultraopt/multi_fidelity/iter/rank_iter.py
ultraopt/multi_fidelity/iter/ws_iter.py
ultraopt/multi_fidelity/iter_gen/__init__.py
ultraopt/multi_fidelity/iter_gen/base_gen.py
ultraopt/multi_fidelity/iter_gen/custom_gen.py
ultraopt/multi_fidelity/iter_gen/hyperband_gen.py
ultraopt/optimizer/__init__.py
ultraopt/optimizer/base_opt.py
ultraopt/optimizer/random_opt.py
ultraopt/optimizer/bo/__init__.py
ultraopt/optimizer/bo/config_evaluator.py
ultraopt/optimizer/bo/etpe_opt.py
ultraopt/optimizer/bo/sampling_sort_opt.py
ultraopt/optimizer/bo/tree_based_opt.py
ultraopt/tests/__init__.py
ultraopt/tests/automl.py
ultraopt/tests/mock.py
ultraopt/utils/__init__.py
ultraopt/utils/config_space.py
ultraopt/utils/config_transformer.py
ultraopt/utils/hash.py
ultraopt/utils/logging.yaml
ultraopt/utils/logging_.py
ultraopt/utils/loss_transformer.py
ultraopt/utils/math_.py
ultraopt/utils/misc.py
ultraopt/utils/net.py
ultraopt/utils/progress.py
ultraopt/utils/std_out_err_redirect_tqdm.py